MANIFEST.in
README
getmail
getmail-gmail-xoauth-tokens
getmail_fetch
getmail_maildir
getmail_mbox
getmails
pyproject.toml
setup.py
./README
dmgetmail6.egg-info/PKG-INFO
dmgetmail6.egg-info/SOURCES.txt
dmgetmail6.egg-info/dependency_links.txt
dmgetmail6.egg-info/top_level.txt
docs/BUGS
docs/CHANGELOG
docs/COPYING
docs/THANKS
docs/configuration.html
docs/configuration.txt
docs/documentation.html
docs/documentation.txt
docs/faq.html
docs/faq.txt
docs/getmail.1
docs/getmail_fetch.1
docs/getmail_maildir.1
docs/getmail_mbox.1
docs/getmaildocs.css
docs/getmailrc-examples
docs/getmails.1
docs/troubleshooting.html
docs/troubleshooting.txt
getmailcore/__init__.py
getmailcore/_retrieverbases.py
getmailcore/baseclasses.py
getmailcore/constants.py
getmailcore/destinations.py
getmailcore/exceptions.py
getmailcore/filters.py
getmailcore/imap_utf7.py
getmailcore/logging.py
getmailcore/message.py
getmailcore/retrievers.py
getmailcore/utilities.py
test/test.py